aemail/__init__.py
aemail/cli.py
aemail/config.py
aemail/data.py
aemail/email_handler.py
aemail/server.py
aemail/static/index.html
aemail/utils.py
aemail/web_api.py
aemail-0.2.3.dist-info/entry_points.txt
aemail-0.2.3.dist-info/METADATA
aemail-0.2.3.dist-info/WHEEL
aemail-0.2.3.dist-info/RECORD
