Metadata-Version: 2.3
Name: aemail
Version: 0.2.3
Summary: A simple SMTP server for receiving emails with REST API access
Keywords: smtp,email,server,api,testing
Author: lycying
Author-email: lycying@example.com
Requires-Python: >=3.8.1,<4.0
Classifier: Development Status :: 4 - Beta
Classifier: Intended Audience :: Developers
Classifier: License :: OSI Approved :: MIT License
Classifier: Operating System :: OS Independent
Classifier: Programming Language :: Python :: 3
Classifier: Programming Language :: Python :: 3.9
Classifier: Programming Language :: Python :: 3.10
Classifier: Programming Language :: Python :: 3.11
Classifier: Programming Language :: Python :: 3.12
Classifier: Programming Language :: Python :: 3.13
Classifier: Programming Language :: Python :: 3.8
Classifier: Topic :: Communications :: Email
Classifier: Topic :: Internet :: WWW/HTTP :: HTTP Servers
Classifier: Topic :: Software Development :: Testing
Requires-Dist: aiosmtpd (>=1.4.4,<2.0.0)
Requires-Dist: flask (>=3.0.0,<4.0.0)
Project-URL: Documentation, https://github.com/lycying/aemail
Project-URL: Homepage, https://github.com/lycying/aemail
Project-URL: Repository, https://github.com/lycying/aemail
